pypyr_scheduler_rpc_client-1.0.2-py3.8-nspkg.pth
pyrsched/rpc/__init__.py
pypyr_scheduler_rpc_client-1.0.2.dist-info/LICENSE
pypyr_scheduler_rpc_client-1.0.2.dist-info/METADATA
pypyr_scheduler_rpc_client-1.0.2.dist-info/WHEEL
pypyr_scheduler_rpc_client-1.0.2.dist-info/namespace_packages.txt
pypyr_scheduler_rpc_client-1.0.2.dist-info/top_level.txt
pypyr_scheduler_rpc_client-1.0.2.dist-info/RECORD
